weather_fetcher/__init__.py
weather_fetcher/api.py
weather_fetcher/core.py
weather_fetcher/server.py
weather_fetcher/utils.py
open_weather_flask-0.1.2.dist-info/LICENSE
open_weather_flask-0.1.2.dist-info/METADATA
open_weather_flask-0.1.2.dist-info/WHEEL
open_weather_flask-0.1.2.dist-info/top_level.txt
open_weather_flask-0.1.2.dist-info/RECORD
